LICENSE
README.md
setup.cfg
setup.py
mc_mod_getter/__init__.py
mc_mod_getter/__main__.py
mc_mod_getter/__version__.py
mc_mod_getter.egg-info/PKG-INFO
mc_mod_getter.egg-info/SOURCES.txt
mc_mod_getter.egg-info/dependency_links.txt
mc_mod_getter.egg-info/not-zip-safe
mc_mod_getter.egg-info/requires.txt
mc_mod_getter.egg-info/top_level.txt
mc_mod_getter/utils/ApiHandler.py
mc_mod_getter/utils/__init__.py